LICENSE
MANIFEST.in
README.rst
setup.cfg
setup.py
docs/Makefile
docs/authors.rst
docs/conf.py
docs/contributing.rst
docs/history.rst
docs/index.rst
docs/installation.rst
docs/make.bat
docs/readme.rst
docs/usage.rst
rlflow/__init__.py
rlflow.egg-info/PKG-INFO
rlflow.egg-info/SOURCES.txt
rlflow.egg-info/dependency_links.txt
rlflow.egg-info/not-zip-safe
rlflow.egg-info/requires.txt
rlflow.egg-info/top_level.txt
rlflow/algos/__init__.py
rlflow/algos/algo.py
rlflow/algos/dp/__init__.py
rlflow/algos/dp/pitr.py
rlflow/algos/dp/vitr.py
rlflow/algos/grad/__init__.py
rlflow/algos/grad/dpg.py
rlflow/algos/grad/grad_algo.py
rlflow/algos/grad/npg.py
rlflow/algos/grad/pg.py
rlflow/algos/prob/__init__.py
rlflow/algos/prob/cem.py
rlflow/algos/td/__init__.py
rlflow/algos/td/dqn.py
rlflow/algos/td/sarsa.py
rlflow/algos/td/td_algo.py
rlflow/core/__init__.py
rlflow/core/rl_utils.py
rlflow/core/tf_utils.py
rlflow/core/input/__init__.py
rlflow/core/input/input_stream_downsampler_processor.py
rlflow/core/input/input_stream_processor.py
rlflow/core/input/input_stream_sequential_processor.py
rlflow/core/output/__init__.py
rlflow/core/output/output_processors.py
rlflow/exploration/__init__.py
rlflow/exploration/egreedy.py
rlflow/exploration/exploration.py
rlflow/memories/__init__.py
rlflow/memories/experience_replay.py
rlflow/policies/__init__.py
rlflow/policies/policy.py
rlflow/policies/tab.py
rlflow/policies/f_approx/__init__.py
rlflow/policies/f_approx/f_approximator.py
rlflow/policies/f_approx/linear.py
rlflow/policies/f_approx/network.py
rlflow/policies/f_approx/rbf.py
tests/__init__.py
tests/test_rlflow.py