Metadata-Version: 1.1
Name: rlflow
Version: 0.1.3
Summary: A framework for learning about and experimenting with reinforcement learning algorithms
Home-page: https://github.com/tpbarron/rlflow
Author: Trevor Barron
Author-email: barron.trevor@gmail.com
License: MIT license
Keywords: FLFlow,TFLearn,TensorFlow,Deep Learning,Reinforcement Learning,Machine Learning,Neural Networks
Platform: UNKNOWN
Classifier: Development Status :: 3 - Alpha
Classifier: Intended Audience :: Science/Research
Classifier: Intended Audience :: Education
Classifier: Topic :: Scientific/Engineering :: Artificial Intelligence
Classifier: License :: OSI Approved :: MIT License
Classifier: Natural Language :: English
Classifier: Programming Language :: Python :: 2
Classifier: Programming Language :: Python :: 2.7
Classifier: Programming Language :: Python :: 3
Classifier: Programming Language :: Python :: 3.5
